[


{
"Name":"ဖြိုးတေဇ",
"Key":"d8d11861a8991ade",
"Valid":"67",
"Expiration":"30\/07\/2024"
},

{
"Name":"ဖြူလေး",
"Key":"58fe806c54938322",
"Valid":"24",
"Expiration":"17\/06\/2024"
},

{
"Name":"စောနေအောင်",
"Key":"3e11b5cb05ce1def",
"Valid":"46",
"Expiration":"09\/07\/2024"
},
  
{
"Name":"KoChitSan",
"Key":"cec9ddc43511557a",
"Valid":"43",
"Expiration":"06\/07\/2024"
},
  
   
{
"Name":"စိုးခိုင်",
"Key":"4022254d94811b96",
"Valid":"15",
"Expiration":"08\/06\/2024"
},
  
{
"Name":"ပြည့်ဖြိုး",
"Key":"3e8b1db83cb22962",
"Valid":"30",
"Expiration":"23\/06\/2024"
},

{
"Name":"zinmar",
"Key":"2ca9644d76e6bc12",
"Valid":"30",
"Expiration":"23\/06\/2024"
},

{
"Name":"ZawZaw",
"Key":"fe2873a2c4e3b4ce",
"Valid":"28",
"Expiration":"22\/06\/2024"
},
  
{
"Name":"ကျော်မြတ်စိုး",
"Key":"4f315d8abefd3c49",
"Valid":"25",
"Expiration":"20\/06\/2024"
},
  
{
"Name":"အိအိလင်း",
"Key":"625e3e9a2fbe7dd1",
"Valid":"30",
"Expiration":"23\/06\/2024"
},

{
"Name":"ငွေကို",
"Key":"29f21fa40528d82b",
"Valid":"17",
"Expiration":"11\/06\/2024"
},  

{
"Name":"Steven",
"Key":"7dfe93671d8749a0",
"Valid":"26",
"Expiration":"18\/06\/2024"
}
  
  
]
